markdown_figcap/__init__.py
markdown_figcap/fig_cap.py
markdown_figcap-0.1.1.dist-info/LICENSE
markdown_figcap-0.1.1.dist-info/METADATA
markdown_figcap-0.1.1.dist-info/WHEEL
markdown_figcap-0.1.1.dist-info/top_level.txt
markdown_figcap-0.1.1.dist-info/RECORD
