Metadata-Version: 2.1
Name: markdown-figcap
Version: 0.1.1
Summary: Extension for Python-Markdown to handle <figure> and <figcaption>.
Home-page: https://github.com/funk1d/markdown-figcap
Author: funkid
Author-email: fuunk1d@g.mailcom
License: BSD License
Platform: UNKNOWN
Classifier: Development Status :: 4 - Beta
Classifier: Intended Audience :: Developers
Classifier: License :: OSI Approved :: BSD License
Classifier: Operating System :: OS Independent
Classifier: Programming Language :: Python
Classifier: Topic :: Text Processing :: Markup :: HTML
Requires-Dist: Markdown (>=3.0.1)
